[
  {
    "rank": 1.0,
    "name": "Saquon Barkley",
    "position": "RB",
    "positionRank": 1.0,
    "originalRank": 1,
    "previousRank": 1,
    "rankChange": 0.0,
    "bye": 9.0,
    "team": "PHI"
  },
  {
    "rank": 2.0,
    "name": "Bijan Robinson",
    "position": "RB",
    "positionRank": 2.0,
    "originalRank": 2,
    "previousRank": 2,
    "rankChange": 0.0,
    "bye": 5.0,
    "team": "ATL"
  },
  {
    "rank": 3.0,
    "name": "Jahmyr Gibbs",
    "position": "RB",
    "positionRank": 3.0,
    "originalRank": 3,
    "previousRank": 3,
    "rankChange": 0.0,
    "bye": 8.0,
    "team": "DET"
  },
  {
    "rank": 4.0,
    "name": "Ja'Marr Chase",
    "position": "WR",
    "positionRank": 1.0,
    "originalRank": 4,
    "previousRank": 4,
    "rankChange": 0.0,
    "bye": 10.0,
    "team": "CIN"
  },
  {
    "rank": 5.0,
    "name": "Justin Jefferson",
    "position": "WR",
    "positionRank": 2.0,
    "originalRank": 5,
    "previousRank": 5,
    "rankChange": 0.0,
    "bye": 6.0,
    "team": "MIN"
  },
  {
    "rank": 6.0,
    "name": "CeeDee Lamb",
    "position": "WR",
    "positionRank": 3.0,
    "originalRank": 6,
    "previousRank": 6,
    "rankChange": 0.0,
    "bye": 10.0,
    "team": "DAL"
  },
  {
    "rank": 7.0,
    "name": "Derrick Henry",
    "position": "RB",
    "positionRank": 4.0,
    "originalRank": 7,
    "previousRank": 7,
    "rankChange": 0.0,
    "bye": 7.0,
    "team": "BAL"
  },
  {
    "rank": 8.0,
    "name": "Christian McCaffrey",
    "position": "RB",
    "positionRank": 5.0,
    "originalRank": 8,
    "previousRank": 8,
    "rankChange": 0.0,
    "bye": 14.0,
    "team": "SF"
  },
  {
    "rank": 9.0,
    "name": "Puka Nacua",
    "position": "WR",
    "positionRank": 4.0,
    "originalRank": 9,
    "previousRank": 9,
    "rankChange": 0.0,
    "bye": 8.0,
    "team": "LAR"
  },
  {
    "rank": 10.0,
    "name": "Nico Collins",
    "position": "WR",
    "positionRank": 5.0,
    "originalRank": 10,
    "previousRank": 10,
    "rankChange": 0.0,
    "bye": 6.0,
    "team": "HOU"
  },
  {
    "rank": 11.0,
    "name": "Amon-Ra St. Brown",
    "position": "WR",
    "positionRank": 6.0,
    "originalRank": 11,
    "previousRank": 11,
    "rankChange": 0.0,
    "bye": 8.0,
    "team": "DET"
  },
  {
    "rank": 12.0,
    "name": "Malik Nabers",
    "position": "WR",
    "positionRank": 7.0,
    "originalRank": 12,
    "previousRank": 12,
    "rankChange": 0.0,
    "bye": 14.0,
    "team": "NYG"
  },
  {
    "rank": 13.0,
    "name": "Josh Jacobs",
    "position": "RB",
    "positionRank": 6.0,
    "originalRank": 13,
    "previousRank": 13,
    "rankChange": 0.0,
    "bye": 5.0,
    "team": "GB"
  },
  {
    "rank": 14.0,
    "name": "Jonathan Taylor",
    "position": "RB",
    "positionRank": 7.0,
    "originalRank": 14,
    "previousRank": 14,
    "rankChange": 0.0,
    "bye": 11.0,
    "team": "IND"
  },
  {
    "rank": 15.0,
    "name": "A.J. Brown",
    "position": "WR",
    "positionRank": 8.0,
    "originalRank": 15,
    "previousRank": 15,
    "rankChange": 0.0,
    "bye": 9.0,
    "team": "PHI"
  },
  {
    "rank": 16.0,
    "name": "Brian Thomas",
    "position": "WR",
    "positionRank": 9.0,
    "originalRank": 16,
    "previousRank": 16,
    "rankChange": 0.0,
    "bye": 8.0,
    "team": "JAX"
  },
  {
    "rank": 17.0,
    "name": "Breece Hall",
    "position": "RB",
    "positionRank": 8.0,
    "originalRank": 17,
    "previousRank": 17,
    "rankChange": 0.0,
    "bye": 9.0,
    "team": "NYJ"
  },
  {
    "rank": 18.0,
    "name": "Ashton Jeanty",
    "position": "RB",
    "positionRank": 9.0,
    "originalRank": 18,
    "previousRank": 18,
    "rankChange": 0.0,
    "bye": 8.0,
    "team": "LV"
  },
  {
    "rank": 19.0,
    "name": "Jaxon Smith-Njigba",
    "position": "WR",
    "positionRank": 10.0,
    "originalRank": 19,
    "previousRank": 19,
    "rankChange": 0.0,
    "bye": 8.0,
    "team": "SEA"
  },
  {
    "rank": 20.0,
    "name": "Kyren Williams",
    "position": "RB",
    "positionRank": 10.0,
    "originalRank": 20,
    "previousRank": 20,
    "rankChange": 0.0,
    "bye": 8.0,
    "team": "LAR"
  },
  {
    "rank": 21.0,
    "name": "Chase Brown",
    "position": "RB",
    "positionRank": 11.0,
    "originalRank": 21,
    "previousRank": 21,
    "rankChange": 0.0,
    "bye": 10.0,
    "team": "CIN"
  },
  {
    "rank": 22.0,
    "name": "De'Von Achane",
    "position": "RB",
    "positionRank": 12.0,
    "originalRank": 22,
    "previousRank": 22,
    "rankChange": 0.0,
    "bye": 12.0,
    "team": "MIA"
  },
  {
    "rank": 23.0,
    "name": "Alvin Kamara",
    "position": "RB",
    "positionRank": 13.0,
    "originalRank": 23,
    "previousRank": 23,
    "rankChange": 0.0,
    "bye": 11.0,
    "team": "NO"
  },
  {
    "rank": 24.0,
    "name": "Tyreek Hill",
    "position": "WR",
    "positionRank": 11.0,
    "originalRank": 24,
    "previousRank": 24,
    "rankChange": 0.0,
    "bye": 12.0,
    "team": "MIA"
  },
  {
    "rank": 25.0,
    "name": "Drake London",
    "position": "WR",
    "positionRank": 12.0,
    "originalRank": 25,
    "previousRank": 25,
    "rankChange": 0.0,
    "bye": 5.0,
    "team": "ATL"
  },
  {
    "rank": 26.0,
    "name": "Ladd McConkey",
    "position": "WR",
    "positionRank": 13.0,
    "originalRank": 26,
    "previousRank": 26,
    "rankChange": 0.0,
    "bye": 12.0,
    "team": "LAC"
  },
  {
    "rank": 27.0,
    "name": "James Cook",
    "position": "RB",
    "positionRank": 14.0,
    "originalRank": 27,
    "previousRank": 27,
    "rankChange": 0.0,
    "bye": 7.0,
    "team": "BUF"
  },
  {
    "rank": 28.0,
    "name": "Brock Bowers",
    "position": "TE",
    "positionRank": 1.0,
    "originalRank": 28,
    "previousRank": 28,
    "rankChange": 0.0,
    "bye": 8.0,
    "team": "LV"
  },
  {
    "rank": 29.0,
    "name": "Trey McBride",
    "position": "TE",
    "positionRank": 2.0,
    "originalRank": 29,
    "previousRank": 29,
    "rankChange": 0.0,
    "bye": 8.0,
    "team": "ARI"
  },
  {
    "rank": 30.0,
    "name": "Chuba Hubbard",
    "position": "RB",
    "positionRank": 15.0,
    "originalRank": 30,
    "previousRank": 30,
    "rankChange": 0.0,
    "bye": 14.0,
    "team": "CAR"
  },
  {
    "rank": 31.0,
    "name": "Bucky Irving",
    "position": "RB",
    "positionRank": 16.0,
    "originalRank": 31,
    "previousRank": 31,
    "rankChange": 0.0,
    "bye": 9.0,
    "team": "TB"
  },
  {
    "rank": 32.0,
    "name": "Kenneth Walker",
    "position": "RB",
    "positionRank": 17.0,
    "originalRank": 32,
    "previousRank": 32,
    "rankChange": 0.0,
    "bye": 8.0,
    "team": "SEA"
  },
  {
    "rank": 33.0,
    "name": "Joe Mixon",
    "position": "RB",
    "positionRank": 18.0,
    "originalRank": 33,
    "previousRank": 33,
    "rankChange": 0.0,
    "bye": 6.0,
    "team": "HOU"
  },
  {
    "rank": 34.0,
    "name": "Terry McLaurin",
    "position": "WR",
    "positionRank": 14.0,
    "originalRank": 34,
    "previousRank": 34,
    "rankChange": 0.0,
    "bye": 12.0,
    "team": "WAS"
  },
  {
    "rank": 35.0,
    "name": "D.J. Moore",
    "position": "WR",
    "positionRank": 15.0,
    "originalRank": 35,
    "previousRank": 35,
    "rankChange": 0.0,
    "bye": null,
    "team": null
  },
  {
    "rank": 36.0,
    "name": "George Kittle",
    "position": "TE",
    "positionRank": 3.0,
    "originalRank": 36,
    "previousRank": 36,
    "rankChange": 0.0,
    "bye": 14.0,
    "team": "SF"
  },
  {
    "rank": 37.0,
    "name": "Garrett Wilson",
    "position": "WR",
    "positionRank": 16.0,
    "originalRank": 37,
    "previousRank": 37,
    "rankChange": 0.0,
    "bye": 9.0,
    "team": "NYJ"
  },
  {
    "rank": 38.0,
    "name": "Lamar Jackson",
    "position": "QB",
    "positionRank": 1.0,
    "originalRank": 38,
    "previousRank": 38,
    "rankChange": 0.0,
    "bye": 7.0,
    "team": "BAL"
  },
  {
    "rank": 39.0,
    "name": "Josh Allen",
    "position": "QB",
    "positionRank": 2.0,
    "originalRank": 39,
    "previousRank": 39,
    "rankChange": 0.0,
    "bye": 7.0,
    "team": "BUF"
  },
  {
    "rank": 40.0,
    "name": "Tee Higgins",
    "position": "WR",
    "positionRank": 17.0,
    "originalRank": 40,
    "previousRank": 40,
    "rankChange": 0.0,
    "bye": 10.0,
    "team": "CIN"
  },
  {
    "rank": 41.0,
    "name": "Davante Adams",
    "position": "WR",
    "positionRank": 18.0,
    "originalRank": 41,
    "previousRank": 41,
    "rankChange": 0.0,
    "bye": 8.0,
    "team": "LAR"
  },
  {
    "rank": 42.0,
    "name": "Zay Flowers",
    "position": "WR",
    "positionRank": 19.0,
    "originalRank": 42,
    "previousRank": 42,
    "rankChange": 0.0,
    "bye": 7.0,
    "team": "BAL"
  },
  {
    "rank": 43.0,
    "name": "Marvin Harrison",
    "position": "WR",
    "positionRank": 20.0,
    "originalRank": 43,
    "previousRank": 43,
    "rankChange": 0.0,
    "bye": 8.0,
    "team": "ARI"
  },
  {
    "rank": 44.0,
    "name": "Rashee Rice",
    "position": "WR",
    "positionRank": 21.0,
    "originalRank": 44,
    "previousRank": 44,
    "rankChange": 0.0,
    "bye": 10.0,
    "team": "KC"
  },
  {
    "rank": 45.0,
    "name": "DK Metcalf",
    "position": "WR",
    "positionRank": 22.0,
    "originalRank": 45,
    "previousRank": 45,
    "rankChange": 0.0,
    "bye": 5.0,
    "team": "PIT"
  },
  {
    "rank": 46.0,
    "name": "James Conner",
    "position": "RB",
    "positionRank": 19.0,
    "originalRank": 46,
    "previousRank": 46,
    "rankChange": 0.0,
    "bye": 8.0,
    "team": "ARI"
  },
  {
    "rank": 47.0,
    "name": "DeVonta Smith",
    "position": "WR",
    "positionRank": 23.0,
    "originalRank": 47,
    "previousRank": 47,
    "rankChange": 0.0,
    "bye": 9.0,
    "team": "PHI"
  },
  {
    "rank": 48.0,
    "name": "Joe Burrow",
    "position": "QB",
    "positionRank": 3.0,
    "originalRank": 48,
    "previousRank": 48,
    "rankChange": 0.0,
    "bye": 10.0,
    "team": "CIN"
  },
  {
    "rank": 49.0,
    "name": "Jayden Daniels",
    "position": "QB",
    "positionRank": 4.0,
    "originalRank": 49,
    "previousRank": 49,
    "rankChange": 0.0,
    "bye": 12.0,
    "team": "WAS"
  },
  {
    "rank": 50.0,
    "name": "Omarion Hampton",
    "position": "RB",
    "positionRank": 20.0,
    "originalRank": 50,
    "previousRank": 50,
    "rankChange": 0.0,
    "bye": 12.0,
    "team": "LAC"
  },
  {
    "rank": 51.0,
    "name": "Mark Andrews",
    "position": "TE",
    "positionRank": 4.0,
    "originalRank": 51,
    "previousRank": 51,
    "rankChange": 0.0,
    "bye": 7.0,
    "team": "BAL"
  },
  {
    "rank": 52.0,
    "name": "Sam LaPorta",
    "position": "TE",
    "positionRank": 5.0,
    "originalRank": 52,
    "previousRank": 52,
    "rankChange": 0.0,
    "bye": 8.0,
    "team": "DET"
  },
  {
    "rank": 53.0,
    "name": "T.J. Hockenson",
    "position": "TE",
    "positionRank": 6.0,
    "originalRank": 53,
    "previousRank": 53,
    "rankChange": 0.0,
    "bye": 6.0,
    "team": "MIN"
  },
  {
    "rank": 54.0,
    "name": "Travis Kelce",
    "position": "TE",
    "positionRank": 7.0,
    "originalRank": 54,
    "previousRank": 54,
    "rankChange": 0.0,
    "bye": 10.0,
    "team": "KC"
  },
  {
    "rank": 55.0,
    "name": "Courtland Sutton",
    "position": "WR",
    "positionRank": 24.0,
    "originalRank": 55,
    "previousRank": 55,
    "rankChange": 0.0,
    "bye": 12.0,
    "team": "DEN"
  },
  {
    "rank": 56.0,
    "name": "Mike Evans",
    "position": "WR",
    "positionRank": 25.0,
    "originalRank": 56,
    "previousRank": 56,
    "rankChange": 0.0,
    "bye": 9.0,
    "team": "TB"
  },
  {
    "rank": 57.0,
    "name": "Jameson Williams",
    "position": "WR",
    "positionRank": 26.0,
    "originalRank": 58,
    "previousRank": 58,
    "rankChange": 1.0,
    "bye": 8.0,
    "team": "DET"
  },
  {
    "rank": 58.0,
    "name": "Ricky Pearsall",
    "position": "WR",
    "positionRank": 27.0,
    "originalRank": 59,
    "previousRank": 59,
    "rankChange": 1.0,
    "bye": 14.0,
    "team": "SF"
  },
  {
    "rank": 59.0,
    "name": "George Pickens",
    "position": "WR",
    "positionRank": 28.0,
    "originalRank": 60,
    "previousRank": 60,
    "rankChange": 1.0,
    "bye": 10.0,
    "team": "DAL"
  },
  {
    "rank": 60.0,
    "name": "Patrick Mahomes",
    "position": "QB",
    "positionRank": 5.0,
    "originalRank": 61,
    "previousRank": 61,
    "rankChange": 1.0,
    "bye": 10.0,
    "team": "KC"
  },
  {
    "rank": 61.0,
    "name": "Jalen Hurts",
    "position": "QB",
    "positionRank": 6.0,
    "originalRank": 62,
    "previousRank": 62,
    "rankChange": 1.0,
    "bye": 9.0,
    "team": "PHI"
  },
  {
    "rank": 62.0,
    "name": "Tyrone Tracy",
    "position": "RB",
    "positionRank": 21.0,
    "originalRank": 63,
    "previousRank": 63,
    "rankChange": 1.0,
    "bye": null,
    "team": null
  },
  {
    "rank": 63.0,
    "name": "Aaron Jones",
    "position": "RB",
    "positionRank": 22.0,
    "originalRank": 64,
    "previousRank": 64,
    "rankChange": 1.0,
    "bye": 6.0,
    "team": "MIN"
  },
  {
    "rank": 64.0,
    "name": "David Montgomery",
    "position": "RB",
    "positionRank": 23.0,
    "originalRank": 65,
    "previousRank": 65,
    "rankChange": 1.0,
    "bye": 8.0,
    "team": "DET"
  },
  {
    "rank": 65.0,
    "name": "Tony Pollard",
    "position": "RB",
    "positionRank": 24.0,
    "originalRank": 66,
    "previousRank": 66,
    "rankChange": 1.0,
    "bye": 10.0,
    "team": "TEN"
  },
  {
    "rank": 66.0,
    "name": "D'Andre Swift",
    "position": "RB",
    "positionRank": 25.0,
    "originalRank": 67,
    "previousRank": 67,
    "rankChange": 1.0,
    "bye": 5.0,
    "team": "CHI"
  },
  {
    "rank": 67.0,
    "name": "Chris Olave",
    "position": "WR",
    "positionRank": 29.0,
    "originalRank": 68,
    "previousRank": 68,
    "rankChange": 1.0,
    "bye": 11.0,
    "team": "NO"
  },
  {
    "rank": 68.0,
    "name": "Jaylen Warren",
    "position": "RB",
    "positionRank": 26.0,
    "originalRank": 69,
    "previousRank": 69,
    "rankChange": 1.0,
    "bye": 5.0,
    "team": "PIT"
  },
  {
    "rank": 69.0,
    "name": "Jerry Jeudy",
    "position": "WR",
    "positionRank": 30.0,
    "originalRank": 70,
    "previousRank": 70,
    "rankChange": 1.0,
    "bye": 9.0,
    "team": "CLE"
  },
  {
    "rank": 70.0,
    "name": "Jaylen Waddle",
    "position": "WR",
    "positionRank": 31.0,
    "originalRank": 71,
    "previousRank": 71,
    "rankChange": 1.0,
    "bye": 12.0,
    "team": "MIA"
  },
  {
    "rank": 71.0,
    "name": "Calvin Ridley",
    "position": "WR",
    "positionRank": 32.0,
    "originalRank": 72,
    "previousRank": 72,
    "rankChange": 1.0,
    "bye": 10.0,
    "team": "TEN"
  },
  {
    "rank": 72.0,
    "name": "Tetairoa McMillan",
    "position": "WR",
    "positionRank": 33.0,
    "originalRank": 98,
    "previousRank": 98,
    "rankChange": 26.0,
    "bye": 14.0,
    "team": "CAR"
  },
  {
    "rank": 73.0,
    "name": "Jordan Addison",
    "position": "WR",
    "positionRank": 34.0,
    "originalRank": 57,
    "previousRank": 57,
    "rankChange": -16.0,
    "bye": 6.0,
    "team": "MIN"
  },
  {
    "rank": 74.0,
    "name": "Chris Godwin",
    "position": "WR",
    "positionRank": 35.0,
    "originalRank": 73,
    "previousRank": 73,
    "rankChange": -1.0,
    "bye": 9.0,
    "team": "TB"
  },
  {
    "rank": 75.0,
    "name": "Isiah Pacheco",
    "position": "RB",
    "positionRank": 27.0,
    "originalRank": 74,
    "previousRank": 74,
    "rankChange": -1.0,
    "bye": 10.0,
    "team": "KC"
  },
  {
    "rank": 76.0,
    "name": "Travis Etienne",
    "position": "RB",
    "positionRank": 28.0,
    "originalRank": 75,
    "previousRank": 75,
    "rankChange": -1.0,
    "bye": null,
    "team": null
  },
  {
    "rank": 77.0,
    "name": "J.K. Dobbins",
    "position": "RB",
    "positionRank": 29.0,
    "originalRank": 76,
    "previousRank": 76,
    "rankChange": -1.0,
    "bye": 12.0,
    "team": "DEN"
  },
  {
    "rank": 78.0,
    "name": "Jauan Jennings",
    "position": "WR",
    "positionRank": 36.0,
    "originalRank": 77,
    "previousRank": 77,
    "rankChange": -1.0,
    "bye": 14.0,
    "team": "SF"
  },
  {
    "rank": 79.0,
    "name": "Rome Odunze",
    "position": "WR",
    "positionRank": 37.0,
    "originalRank": 78,
    "previousRank": 78,
    "rankChange": -1.0,
    "bye": 5.0,
    "team": "CHI"
  },
  {
    "rank": 80.0,
    "name": "Rachaad White",
    "position": "RB",
    "positionRank": 30.0,
    "originalRank": 79,
    "previousRank": 79,
    "rankChange": -1.0,
    "bye": null,
    "team": null
  },
  {
    "rank": 81.0,
    "name": "Deebo Samuel",
    "position": "WR",
    "positionRank": 38.0,
    "originalRank": 80,
    "previousRank": 80,
    "rankChange": -1.0,
    "bye": 12.0,
    "team": "WAS"
  },
  {
    "rank": 82.0,
    "name": "Jakobi Meyers",
    "position": "WR",
    "positionRank": 39.0,
    "originalRank": 81,
    "previousRank": 81,
    "rankChange": -1.0,
    "bye": 8.0,
    "team": "LV"
  },
  {
    "rank": 83.0,
    "name": "Travis Hunter",
    "position": "WR",
    "positionRank": 40.0,
    "originalRank": 83,
    "previousRank": 83,
    "rankChange": 0.0,
    "bye": 8.0,
    "team": "JAX"
  },
  {
    "rank": 84.0,
    "name": "Xavier Worthy",
    "position": "WR",
    "positionRank": 41.0,
    "originalRank": 84,
    "previousRank": 84,
    "rankChange": 0.0,
    "bye": 10.0,
    "team": "KC"
  },
  {
    "rank": 85.0,
    "name": "Stefon Diggs",
    "position": "WR",
    "positionRank": 42.0,
    "originalRank": 85,
    "previousRank": 85,
    "rankChange": 0.0,
    "bye": 14.0,
    "team": "NE"
  },
  {
    "rank": 86.0,
    "name": "Emeka Egbuka",
    "position": "WR",
    "positionRank": 43.0,
    "originalRank": 116,
    "previousRank": 116,
    "rankChange": 30.0,
    "bye": 9.0,
    "team": "TB"
  },
  {
    "rank": 87.0,
    "name": "Jayden Reed",
    "position": "WR",
    "positionRank": 44.0,
    "originalRank": 82,
    "previousRank": 82,
    "rankChange": -5.0,
    "bye": 5.0,
    "team": "GB"
  },
  {
    "rank": 88.0,
    "name": "Cooper Kupp",
    "position": "WR",
    "positionRank": 45.0,
    "originalRank": 86,
    "previousRank": 86,
    "rankChange": -2.0,
    "bye": 8.0,
    "team": "SEA"
  },
  {
    "rank": 89.0,
    "name": "Austin Ekeler",
    "position": "RB",
    "positionRank": 31.0,
    "originalRank": 88,
    "previousRank": 88,
    "rankChange": -1.0,
    "bye": 12.0,
    "team": "WAS"
  },
  {
    "rank": 90.0,
    "name": "Tank Bigsby",
    "position": "RB",
    "positionRank": 32.0,
    "originalRank": 89,
    "previousRank": 89,
    "rankChange": -1.0,
    "bye": null,
    "team": null
  },
  {
    "rank": 91.0,
    "name": "Kaleb Johnson",
    "position": "RB",
    "positionRank": 33.0,
    "originalRank": 90,
    "previousRank": 90,
    "rankChange": -1.0,
    "bye": 5.0,
    "team": "PIT"
  },
  {
    "rank": 92.0,
    "name": "Brian Robinson",
    "position": "RB",
    "positionRank": 34.0,
    "originalRank": 91,
    "previousRank": 91,
    "rankChange": -1.0,
    "bye": 12.0,
    "team": "WAS"
  },
  {
    "rank": 93.0,
    "name": "TreVeyon Henderson",
    "position": "RB",
    "positionRank": 35.0,
    "originalRank": 92,
    "previousRank": 92,
    "rankChange": -1.0,
    "bye": 14.0,
    "team": "NE"
  },
  {
    "rank": 94.0,
    "name": "R.J. Harvey",
    "position": "RB",
    "positionRank": 36.0,
    "originalRank": 93,
    "previousRank": 93,
    "rankChange": -1.0,
    "bye": null,
    "team": null
  },
  {
    "rank": 95.0,
    "name": "Jerome Ford",
    "position": "RB",
    "positionRank": 37.0,
    "originalRank": 94,
    "previousRank": 94,
    "rankChange": -1.0,
    "bye": null,
    "team": null
  },
  {
    "rank": 96.0,
    "name": "Michael Pittman",
    "position": "WR",
    "positionRank": 46.0,
    "originalRank": 95,
    "previousRank": 95,
    "rankChange": -1.0,
    "bye": null,
    "team": null
  },
  {
    "rank": 97.0,
    "name": "Khalil Shakir",
    "position": "WR",
    "positionRank": 47.0,
    "originalRank": 96,
    "previousRank": 96,
    "rankChange": -1.0,
    "bye": 7.0,
    "team": "BUF"
  },
  {
    "rank": 98.0,
    "name": "Zach Charbonnet",
    "position": "RB",
    "positionRank": 38.0,
    "originalRank": 97,
    "previousRank": 97,
    "rankChange": -1.0,
    "bye": null,
    "team": null
  },
  {
    "rank": 99.0,
    "name": "Keenan Allen",
    "position": "WR",
    "positionRank": 48.0,
    "originalRank": 99,
    "previousRank": 99,
    "rankChange": 0.0,
    "bye": null,
    "team": null
  },
  {
    "rank": 100.0,
    "name": "Josh Downs",
    "position": "WR",
    "positionRank": 49.0,
    "originalRank": 99,
    "previousRank": 99,
    "rankChange": -1.0,
    "bye": 11.0,
    "team": "IND"
  },
  {
    "rank": 101.0,
    "name": "Najee Harris",
    "position": "RB",
    "positionRank": 39.0,
    "originalRank": 100,
    "previousRank": 100,
    "rankChange": -1.0,
    "bye": null,
    "team": null
  },
  {
    "rank": 102.0,
    "name": "Justin Herbert",
    "position": "QB",
    "positionRank": 7.0,
    "originalRank": 101,
    "previousRank": 101,
    "rankChange": -1.0,
    "bye": 12.0,
    "team": "LAC"
  },
  {
    "rank": 103.0,
    "name": "Jared Goff",
    "position": "QB",
    "positionRank": 8.0,
    "originalRank": 102,
    "previousRank": 102,
    "rankChange": -1.0,
    "bye": 8.0,
    "team": "DET"
  },
  {
    "rank": 104.0,
    "name": "Rhamondre Stevenson",
    "position": "RB",
    "positionRank": 40.0,
    "originalRank": 103,
    "previousRank": 103,
    "rankChange": -1.0,
    "bye": null,
    "team": null
  },
  {
    "rank": 105.0,
    "name": "Jordan Mason",
    "position": "RB",
    "positionRank": 41.0,
    "originalRank": 104,
    "previousRank": 104,
    "rankChange": -1.0,
    "bye": null,
    "team": null
  },
  {
    "rank": 106.0,
    "name": "Brandon Aiyuk",
    "position": "WR",
    "positionRank": 50.0,
    "originalRank": 105,
    "previousRank": 105,
    "rankChange": -1.0,
    "bye": null,
    "team": null
  },
  {
    "rank": 107.0,
    "name": "Javonte Williams",
    "position": "RB",
    "positionRank": 42.0,
    "originalRank": 107,
    "previousRank": 107,
    "rankChange": 0.0,
    "bye": null,
    "team": null
  },
  {
    "rank": 108.0,
    "name": "Jaylen Wright",
    "position": "RB",
    "positionRank": 43.0,
    "originalRank": 108,
    "previousRank": 108,
    "rankChange": 0.0,
    "bye": null,
    "team": null
  },
  {
    "rank": 109.0,
    "name": "Ray Davis",
    "position": "RB",
    "positionRank": 44.0,
    "originalRank": 109,
    "previousRank": 109,
    "rankChange": 0.0,
    "bye": null,
    "team": null
  },
  {
    "rank": 110.0,
    "name": "Colston Loveland",
    "position": "TE",
    "positionRank": 8.0,
    "originalRank": 110,
    "previousRank": 110,
    "rankChange": 0.0,
    "bye": null,
    "team": null
  },
  {
    "rank": 111.0,
    "name": "Tyler Warren",
    "position": "TE",
    "positionRank": 9.0,
    "originalRank": 111,
    "previousRank": 111,
    "rankChange": 0.0,
    "bye": null,
    "team": null
  },
  {
    "rank": 112.0,
    "name": "Dalton Kincaid",
    "position": "TE",
    "positionRank": 10.0,
    "originalRank": 112,
    "previousRank": 112,
    "rankChange": 0.0,
    "bye": null,
    "team": null
  },
  {
    "rank": 113.0,
    "name": "Tucker Kraft",
    "position": "TE",
    "positionRank": 11.0,
    "originalRank": 113,
    "previousRank": 113,
    "rankChange": 0.0,
    "bye": 5.0,
    "team": "GB"
  },
  {
    "rank": 114.0,
    "name": "Matthew Golden",
    "position": "WR",
    "positionRank": 51.0,
    "originalRank": 114,
    "previousRank": 114,
    "rankChange": 0.0,
    "bye": 5.0,
    "team": "GB"
  },
  {
    "rank": 115.0,
    "name": "Luther Burden",
    "position": "WR",
    "positionRank": 52.0,
    "originalRank": 115,
    "previousRank": 115,
    "rankChange": 0.0,
    "bye": null,
    "team": null
  },
  {
    "rank": 116.0,
    "name": "Jayden Higgins",
    "position": "WR",
    "positionRank": 53.0,
    "originalRank": 117,
    "previousRank": 117,
    "rankChange": 1.0,
    "bye": null,
    "team": null
  },
  {
    "rank": 117.0,
    "name": "C.J. Stroud",
    "position": "QB",
    "positionRank": 9.0,
    "originalRank": 118,
    "previousRank": 118,
    "rankChange": 1.0,
    "bye": 6.0,
    "team": "HOU"
  },
  {
    "rank": 118.0,
    "name": "Brock Purdy",
    "position": "QB",
    "positionRank": 10.0,
    "originalRank": 119,
    "previousRank": 119,
    "rankChange": 1.0,
    "bye": 14.0,
    "team": "SF"
  },
  {
    "rank": 119.0,
    "name": "Jordan Love",
    "position": "QB",
    "positionRank": 11.0,
    "originalRank": 120,
    "previousRank": 120,
    "rankChange": 1.0,
    "bye": 5.0,
    "team": "GB"
  },
  {
    "rank": 120.0,
    "name": "Baker Mayfield",
    "position": "QB",
    "positionRank": 12.0,
    "originalRank": 121,
    "previousRank": 121,
    "rankChange": 1.0,
    "bye": 9.0,
    "team": "TB"
  },
  {
    "rank": 121.0,
    "name": "Tyler Allgeier",
    "position": "RB",
    "positionRank": 45.0,
    "originalRank": 123,
    "previousRank": 123,
    "rankChange": 2.0,
    "bye": null,
    "team": null
  },
  {
    "rank": 122.0,
    "name": "Cam Skattebo",
    "position": "RB",
    "positionRank": 46.0,
    "originalRank": 124,
    "previousRank": 124,
    "rankChange": 2.0,
    "bye": null,
    "team": null
  },
  {
    "rank": 123.0,
    "name": "Blake Corum",
    "position": "RB",
    "positionRank": 47.0,
    "originalRank": 125,
    "previousRank": 125,
    "rankChange": 2.0,
    "bye": null,
    "team": null
  },
  {
    "rank": 124.0,
    "name": "Rico Dowdle",
    "position": "RB",
    "positionRank": 48.0,
    "originalRank": 126,
    "previousRank": 126,
    "rankChange": 2.0,
    "bye": null,
    "team": null
  },
  {
    "rank": 125.0,
    "name": "Christian Kirk",
    "position": "WR",
    "positionRank": 54.0,
    "originalRank": 127,
    "previousRank": 127,
    "rankChange": 2.0,
    "bye": 6.0,
    "team": "HOU"
  },
  {
    "rank": 126.0,
    "name": "Keon Coleman",
    "position": "WR",
    "positionRank": 55.0,
    "originalRank": 128,
    "previousRank": 128,
    "rankChange": 2.0,
    "bye": 7.0,
    "team": "BUF"
  },
  {
    "rank": 127.0,
    "name": "Darnell Mooney",
    "position": "WR",
    "positionRank": 56.0,
    "originalRank": 129,
    "previousRank": 129,
    "rankChange": 2.0,
    "bye": 5.0,
    "team": "ATL"
  },
  {
    "rank": 128.0,
    "name": "Demario Douglas",
    "position": "WR",
    "positionRank": 57.0,
    "originalRank": 191,
    "previousRank": 191,
    "rankChange": 63.0,
    "bye": null,
    "team": null
  },
  {
    "rank": 129.0,
    "name": "Adam Thielen",
    "position": "WR",
    "positionRank": 58.0,
    "originalRank": 130,
    "previousRank": 130,
    "rankChange": 1.0,
    "bye": 14.0,
    "team": "CAR"
  },
  {
    "rank": 130.0,
    "name": "Romeo Doubs",
    "position": "WR",
    "positionRank": 59.0,
    "originalRank": 131,
    "previousRank": 131,
    "rankChange": 1.0,
    "bye": null,
    "team": null
  },
  {
    "rank": 131.0,
    "name": "Evan Engram",
    "position": "TE",
    "positionRank": 12.0,
    "originalRank": 132,
    "previousRank": 132,
    "rankChange": 1.0,
    "bye": 12.0,
    "team": "DEN"
  },
  {
    "rank": 132.0,
    "name": "Dallas Goedert",
    "position": "TE",
    "positionRank": 13.0,
    "originalRank": 133,
    "previousRank": 133,
    "rankChange": 1.0,
    "bye": null,
    "team": null
  },
  {
    "rank": 133.0,
    "name": "David Njoku",
    "position": "TE",
    "positionRank": 14.0,
    "originalRank": 134,
    "previousRank": 134,
    "rankChange": 1.0,
    "bye": 9.0,
    "team": "CLE"
  },
  {
    "rank": 134.0,
    "name": "Jonnu Smith",
    "position": "TE",
    "positionRank": 15.0,
    "originalRank": 87,
    "previousRank": 87,
    "rankChange": -47.0,
    "bye": null,
    "team": null
  },
  {
    "rank": 135.0,
    "name": "Trey Benson",
    "position": "RB",
    "positionRank": 49.0,
    "originalRank": 135,
    "previousRank": 135,
    "rankChange": 0.0,
    "bye": null,
    "team": null
  },
  {
    "rank": 136.0,
    "name": "Dylan Sampson",
    "position": "RB",
    "positionRank": 50.0,
    "originalRank": 137,
    "previousRank": 137,
    "rankChange": 1.0,
    "bye": null,
    "team": null
  },
  {
    "rank": 137.0,
    "name": "Tyjae Spears",
    "position": "RB",
    "positionRank": 51.0,
    "originalRank": 106,
    "previousRank": 106,
    "rankChange": -31.0,
    "bye": null,
    "team": null
  },
  {
    "rank": 138.0,
    "name": "Keaton Mitchell",
    "position": "RB",
    "positionRank": 52.0,
    "originalRank": 138,
    "previousRank": 138,
    "rankChange": 0.0,
    "bye": null,
    "team": null
  },
  {
    "rank": 139.0,
    "name": "Braelon Allen",
    "position": "RB",
    "positionRank": 53.0,
    "originalRank": 139,
    "previousRank": 139,
    "rankChange": 0.0,
    "bye": null,
    "team": null
  },
  {
    "rank": 140.0,
    "name": "Isaac Guerendo",
    "position": "RB",
    "positionRank": 54.0,
    "originalRank": 136,
    "previousRank": 136,
    "rankChange": -4.0,
    "bye": null,
    "team": null
  },
  {
    "rank": 141.0,
    "name": "Rashid Shaheed",
    "position": "WR",
    "positionRank": 60.0,
    "originalRank": 140,
    "previousRank": 140,
    "rankChange": -1.0,
    "bye": 11.0,
    "team": "NO"
  },
  {
    "rank": 142.0,
    "name": "Cedric Tillman",
    "position": "WR",
    "positionRank": 61.0,
    "originalRank": 141,
    "previousRank": 141,
    "rankChange": -1.0,
    "bye": 9.0,
    "team": "CLE"
  },
  {
    "rank": 143.0,
    "name": "Jalen McMillan",
    "position": "WR",
    "positionRank": 62.0,
    "originalRank": 142,
    "previousRank": 142,
    "rankChange": -1.0,
    "bye": null,
    "team": null
  },
  {
    "rank": 144.0,
    "name": "Wan'Dale Robinson",
    "position": "WR",
    "positionRank": 63.0,
    "originalRank": 143,
    "previousRank": 143,
    "rankChange": -1.0,
    "bye": 14.0,
    "team": "NYG"
  },
  {
    "rank": 145.0,
    "name": "Kyler Murray",
    "position": "QB",
    "positionRank": 13.0,
    "originalRank": 144,
    "previousRank": 144,
    "rankChange": -1.0,
    "bye": 8.0,
    "team": "ARI"
  },
  {
    "rank": 146.0,
    "name": "Drake Maye",
    "position": "QB",
    "positionRank": 14.0,
    "originalRank": 145,
    "previousRank": 145,
    "rankChange": -1.0,
    "bye": 14.0,
    "team": "NE"
  },
  {
    "rank": 147.0,
    "name": "Caleb Williams",
    "position": "QB",
    "positionRank": 15.0,
    "originalRank": 146,
    "previousRank": 146,
    "rankChange": -1.0,
    "bye": 5.0,
    "team": "CHI"
  },
  {
    "rank": 148.0,
    "name": "Jaylin Noel",
    "position": "WR",
    "positionRank": 64.0,
    "originalRank": 147,
    "previousRank": 147,
    "rankChange": -1.0,
    "bye": null,
    "team": null
  },
  {
    "rank": 149.0,
    "name": "Xavier Legette",
    "position": "WR",
    "positionRank": 65.0,
    "originalRank": 148,
    "previousRank": 148,
    "rankChange": -1.0,
    "bye": null,
    "team": null
  },
  {
    "rank": 150.0,
    "name": "Rashod Bateman",
    "position": "WR",
    "positionRank": 66.0,
    "originalRank": 149,
    "previousRank": 149,
    "rankChange": -1.0,
    "bye": null,
    "team": null
  },
  {
    "rank": 151.0,
    "name": "Dontayvion Wicks",
    "position": "WR",
    "positionRank": 67.0,
    "originalRank": 150,
    "previousRank": 150,
    "rankChange": -1.0,
    "bye": null,
    "team": null
  },
  {
    "rank": 152.0,
    "name": "Alec Pierce",
    "position": "WR",
    "positionRank": 68.0,
    "originalRank": 151,
    "previousRank": 151,
    "rankChange": -1.0,
    "bye": null,
    "team": null
  },
  {
    "rank": 153.0,
    "name": "Kendre Miller",
    "position": "RB",
    "positionRank": 55.0,
    "originalRank": 152,
    "previousRank": 152,
    "rankChange": -1.0,
    "bye": null,
    "team": null
  },
  {
    "rank": 154.0,
    "name": "Woody Marks",
    "position": "RB",
    "positionRank": 56.0,
    "originalRank": 153,
    "previousRank": 153,
    "rankChange": -1.0,
    "bye": null,
    "team": null
  },
  {
    "rank": 155.0,
    "name": "Elijah Mitchell",
    "position": "RB",
    "positionRank": 57.0,
    "originalRank": 154,
    "previousRank": 154,
    "rankChange": -1.0,
    "bye": null,
    "team": null
  },
  {
    "rank": 156.0,
    "name": "MarShawn Lloyd",
    "position": "RB",
    "positionRank": 58.0,
    "originalRank": 155,
    "previousRank": 155,
    "rankChange": -1.0,
    "bye": null,
    "team": null
  },
  {
    "rank": 157.0,
    "name": "Jordan James",
    "position": "RB",
    "positionRank": 59.0,
    "originalRank": 200,
    "previousRank": 200,
    "rankChange": 43.0,
    "bye": null,
    "team": null
  },
  {
    "rank": 158.0,
    "name": "Quinshon Judkins",
    "position": "RB",
    "positionRank": 60.0,
    "originalRank": 122,
    "previousRank": 122,
    "rankChange": -36.0,
    "bye": null,
    "team": null
  },
  {
    "rank": 159.0,
    "name": "Trevor Etienne",
    "position": "RB",
    "positionRank": 61.0,
    "originalRank": 156,
    "previousRank": 156,
    "rankChange": -3.0,
    "bye": null,
    "team": null
  },
  {
    "rank": 160.0,
    "name": "Will Shipley",
    "position": "RB",
    "positionRank": 62.0,
    "originalRank": 157,
    "previousRank": 157,
    "rankChange": -3.0,
    "bye": null,
    "team": null
  },
  {
    "rank": 161,
    "name": "Josh Palmer",
    "position": "WR",
    "positionRank": 75.0,
    "originalRank": 181,
    "previousRank": 181,
    "rankChange": null,
    "bye": null,
    "team": null
  },
  {
    "rank": 162,
    "name": "Bo Nix",
    "position": "QB",
    "positionRank": 20.0,
    "originalRank": 178,
    "previousRank": 178,
    "rankChange": null,
    "bye": 12.0,
    "team": "DEN"
  },
  {
    "rank": 163,
    "name": "Dak Prescott",
    "position": "QB",
    "positionRank": 17.0,
    "originalRank": 175,
    "previousRank": 175,
    "rankChange": null,
    "bye": 10.0,
    "team": "DAL"
  },
  {
    "rank": 164,
    "name": "DJ Giddens",
    "position": "RB",
    "positionRank": 66.0,
    "originalRank": 171,
    "previousRank": 171,
    "rankChange": null,
    "bye": null,
    "team": null
  },
  {
    "rank": 165,
    "name": "Isaiah Likely",
    "position": "TE",
    "positionRank": 18.0,
    "originalRank": 169,
    "previousRank": 169,
    "rankChange": null,
    "bye": null,
    "team": null
  },
  {
    "rank": 166,
    "name": "Tahj Brooks",
    "position": "RB",
    "positionRank": 63.0,
    "originalRank": 159,
    "previousRank": 159,
    "rankChange": null,
    "bye": null,
    "team": null
  },
  {
    "rank": 167,
    "name": "Audric Estim\u00e9",
    "position": "RB",
    "positionRank": 70.0,
    "originalRank": 184,
    "previousRank": 184,
    "rankChange": null,
    "bye": null,
    "team": null
  },
  {
    "rank": 168,
    "name": "Tre Harris",
    "position": "WR",
    "positionRank": 69.0,
    "originalRank": 163,
    "previousRank": 163,
    "rankChange": null,
    "bye": null,
    "team": null
  },
  {
    "rank": 169,
    "name": "Diontae Johnson",
    "position": "WR",
    "positionRank": 79.0,
    "originalRank": 192,
    "previousRank": 192,
    "rankChange": null,
    "bye": null,
    "team": null
  },
  {
    "rank": 170,
    "name": "Justice Hill",
    "position": "RB",
    "positionRank": 73.0,
    "originalRank": 187,
    "previousRank": 187,
    "rankChange": null,
    "bye": null,
    "team": null
  },
  {
    "rank": 171,
    "name": "Michael Wilson",
    "position": "WR",
    "positionRank": 72.0,
    "originalRank": 166,
    "previousRank": 166,
    "rankChange": null,
    "bye": null,
    "team": null
  },
  {
    "rank": 172,
    "name": "Tua Tagovailoa",
    "position": "QB",
    "positionRank": 18.0,
    "originalRank": 176,
    "previousRank": 176,
    "rankChange": null,
    "bye": null,
    "team": null
  },
  {
    "rank": 173,
    "name": "Quentin Johnston",
    "position": "WR",
    "positionRank": 67.0,
    "originalRank": 161,
    "previousRank": 161,
    "rankChange": null,
    "bye": null,
    "team": null
  },
  {
    "rank": 174,
    "name": "Kenneth Gainwell",
    "position": "RB",
    "positionRank": 74.0,
    "originalRank": 188,
    "previousRank": 188,
    "rankChange": null,
    "bye": null,
    "team": null
  },
  {
    "rank": 175,
    "name": "Marquise Brown",
    "position": "WR",
    "positionRank": 70.0,
    "originalRank": 164,
    "previousRank": 164,
    "rankChange": null,
    "bye": 10.0,
    "team": "KC"
  },
  {
    "rank": 176,
    "name": "Geno Smith",
    "position": "QB",
    "positionRank": 25.0,
    "originalRank": 197,
    "previousRank": 197,
    "rankChange": null,
    "bye": null,
    "team": null
  },
  {
    "rank": 177,
    "name": "DeAndre Hopkins",
    "position": "WR",
    "positionRank": 73.0,
    "originalRank": 179,
    "previousRank": 179,
    "rankChange": null,
    "bye": null,
    "team": null
  },
  {
    "rank": 178,
    "name": "Kimani Vidal",
    "position": "RB",
    "positionRank": 72.0,
    "originalRank": 186,
    "previousRank": 186,
    "rankChange": null,
    "bye": null,
    "team": null
  },
  {
    "rank": 179,
    "name": "Michael Penix",
    "position": "QB",
    "positionRank": 23.0,
    "originalRank": 195,
    "previousRank": 195,
    "rankChange": null,
    "bye": null,
    "team": null
  },
  {
    "rank": 180,
    "name": "Jack Bech",
    "position": "WR",
    "positionRank": 68.0,
    "originalRank": 162,
    "previousRank": 162,
    "rankChange": null,
    "bye": null,
    "team": null
  },
  {
    "rank": 181,
    "name": "Jaydon Blue",
    "position": "RB",
    "positionRank": 62.0,
    "originalRank": 158,
    "previousRank": 158,
    "rankChange": null,
    "bye": null,
    "team": null
  },
  {
    "rank": 182,
    "name": "Nick Chubb",
    "position": "RB",
    "positionRank": 64.0,
    "originalRank": 160,
    "previousRank": 160,
    "rankChange": null,
    "bye": null,
    "team": null
  },
  {
    "rank": 183,
    "name": "Jalen Royals",
    "position": "WR",
    "positionRank": 77.0,
    "originalRank": 190,
    "previousRank": 190,
    "rankChange": null,
    "bye": null,
    "team": null
  },
  {
    "rank": 184,
    "name": "Ty Johnson",
    "position": "RB",
    "positionRank": 75.0,
    "originalRank": 189,
    "previousRank": 189,
    "rankChange": null,
    "bye": null,
    "team": null
  },
  {
    "rank": 185,
    "name": "Cade Otton",
    "position": "TE",
    "positionRank": 16.0,
    "originalRank": 167,
    "previousRank": 167,
    "rankChange": null,
    "bye": null,
    "team": null
  },
  {
    "rank": 186,
    "name": "Kyle Williams",
    "position": "WR",
    "positionRank": 71.0,
    "originalRank": 165,
    "previousRank": 165,
    "rankChange": null,
    "bye": null,
    "team": null
  },
  {
    "rank": 187,
    "name": "Jalen Coker",
    "position": "WR",
    "positionRank": 74.0,
    "originalRank": 180,
    "previousRank": 180,
    "rankChange": null,
    "bye": null,
    "team": null
  },
  {
    "rank": 188,
    "name": "Dameon Pierce",
    "position": "RB",
    "positionRank": 71.0,
    "originalRank": 185,
    "previousRank": 185,
    "rankChange": null,
    "bye": null,
    "team": null
  },
  {
    "rank": 189,
    "name": "Kyle Pitts",
    "position": "TE",
    "positionRank": 17.0,
    "originalRank": 168,
    "previousRank": 168,
    "rankChange": null,
    "bye": null,
    "team": null
  },
  {
    "rank": 190,
    "name": "Justin Fields",
    "position": "QB",
    "positionRank": 16.0,
    "originalRank": 174,
    "previousRank": 174,
    "rankChange": null,
    "bye": 9.0,
    "team": "NYJ"
  },
  {
    "rank": 191,
    "name": "Antonio Gibson",
    "position": "RB",
    "positionRank": 67.0,
    "originalRank": 172,
    "previousRank": 172,
    "rankChange": null,
    "bye": null,
    "team": null
  },
  {
    "rank": 192,
    "name": "Brashard Smith",
    "position": "RB",
    "positionRank": 68.0,
    "originalRank": 173,
    "previousRank": 173,
    "rankChange": null,
    "bye": null,
    "team": null
  },
  {
    "rank": 193,
    "name": "Bryce Young",
    "position": "QB",
    "positionRank": 24.0,
    "originalRank": 196,
    "previousRank": 196,
    "rankChange": null,
    "bye": null,
    "team": null
  },
  {
    "rank": 194,
    "name": "Elic Ayomanor",
    "position": "WR",
    "positionRank": 80.0,
    "originalRank": 199,
    "previousRank": 199,
    "rankChange": null,
    "bye": null,
    "team": null
  },
  {
    "rank": 195,
    "name": "Damien Martinez",
    "position": "RB",
    "positionRank": 65.0,
    "originalRank": 170,
    "previousRank": 170,
    "rankChange": null,
    "bye": null,
    "team": null
  },
  {
    "rank": 196,
    "name": "Matthew Stafford",
    "position": "QB",
    "positionRank": 22.0,
    "originalRank": 194,
    "previousRank": 194,
    "rankChange": null,
    "bye": null,
    "team": null
  },
  {
    "rank": 197,
    "name": "Roschon Johnson",
    "position": "RB",
    "positionRank": 69.0,
    "originalRank": 183,
    "previousRank": 183,
    "rankChange": null,
    "bye": null,
    "team": null
  },
  {
    "rank": 198,
    "name": "Sam Darnold",
    "position": "QB",
    "positionRank": 26.0,
    "originalRank": 198,
    "previousRank": 198,
    "rankChange": null,
    "bye": null,
    "team": null
  },
  {
    "rank": 199,
    "name": "Trevor Lawrence",
    "position": "QB",
    "positionRank": 21.0,
    "originalRank": 193,
    "previousRank": 193,
    "rankChange": null,
    "bye": null,
    "team": null
  },
  {
    "rank": 200,
    "name": "J.J. McCarthy",
    "position": "QB",
    "positionRank": 19.0,
    "originalRank": 177,
    "previousRank": 177,
    "rankChange": null,
    "bye": 6.0,
    "team": "MIN"
  },
  {
    "rank": 201,
    "name": "Marvin Mims",
    "position": "WR",
    "positionRank": 76.0,
    "originalRank": 182,
    "previousRank": 182,
    "rankChange": null,
    "bye": null,
    "team": null
  }
]
